maudeSE/__init__.py
maudeSE/config.yml
maudeSE/connector/cvc5.py
maudeSE/connector/yices.py
maudeSE/connector/z3.py
maudeSE/converter/cvc5.py
maudeSE/converter/yices.py
maudeSE/converter/z3.py
maudeSE/factory.py
maudeSE/maude/__init__.py
maudeSE/maude/_maude.so
maudeSE/maude/file.maude
maudeSE/maude/libmaude.dylib
maudeSE/maude/linear.maude
maudeSE/maude/machine-int.maude
maudeSE/maude/maude-se-meta.maude
maudeSE/maude/metaInterpreter.maude
maudeSE/maude/model-checker.maude
maudeSE/maude/prelude.maude
maudeSE/maude/process.maude
maudeSE/maude/smt-check.maude
maudeSE/maude/smt.maude
maudeSE/maude/socket.maude
maudeSE/maude/term-order.maude
maudeSE/maude/time.maude
maudeSE/util.py
maude_se-0.0.3.dist-info/METADATA
maude_se-0.0.3.dist-info/WHEEL
maude_se-0.0.3.dist-info/entry_points.txt
maude_se-0.0.3.dist-info/licenses/LICENSE
maude_se-0.0.3.dist-info/RECORD
