Metadata-Version: 2.2
Name: maude-se
Version: 0.0.3
Summary: Maude SMT Extension
Author-Email: Geunyeol Yu <maude-se@postech.ac.kr>
License: GPLv3
Classifier: Intended Audience :: Science/Research
Classifier: Programming Language :: Python
Classifier: Programming Language :: Python :: 3
Classifier: Topic :: Scientific/Engineering
Classifier: Operating System :: OS Independent
Project-URL: Homepage, https://maude-se.github.io
Project-URL: Bug Tracker, https://github.com/postechsv/maude-se/issues
Project-URL: Documentation, https://maude-se.github.io
Project-URL: Source Code, https://github.com/postechsv/maude-se
Requires-Dist: pyyaml
